restutil/__init__.py
restutil/restutil.py
restutil/urlmaker.py
restutil_tjdaley-0.0.2.dist-info/LICENSE
restutil_tjdaley-0.0.2.dist-info/METADATA
restutil_tjdaley-0.0.2.dist-info/WHEEL
restutil_tjdaley-0.0.2.dist-info/top_level.txt
restutil_tjdaley-0.0.2.dist-info/RECORD
